smail.py
simplemail_cli-0.1.1.dist-info/METADATA
simplemail_cli-0.1.1.dist-info/WHEEL
simplemail_cli-0.1.1.dist-info/entry_points.txt
simplemail_cli-0.1.1.dist-info/top_level.txt
simplemail_cli-0.1.1.dist-info/RECORD
