Metadata-Version: 2.4
Name: simplemail-cli
Version: 0.1.1
Summary: A simple mail client CLI
Author-email: Adrian Galilea <adriangalilea@gmail.com>
Project-URL: Homepage, https://github.com/adriangalilea/smail
Project-URL: Repository, https://github.com/adriangalilea/smail
Project-URL: Issues, https://github.com/adriangalilea/smail/issues
Requires-Python: >=3.12
Requires-Dist: rich>=13.0.0
